README.md
setup.cfg
setup.py
distributions_new/Binomialdistribution.py
distributions_new/Gaussiandistribution.py
distributions_new/Generaldistribution.py
distributions_new/__init__.py
distributions_new.egg-info/PKG-INFO
distributions_new.egg-info/SOURCES.txt
distributions_new.egg-info/dependency_links.txt
distributions_new.egg-info/not-zip-safe
distributions_new.egg-info/top_level.txt